[
  {
    "ContainingType": "SmartBin.Api.Controllers.BinController",
    "Method": "GetBins",
    "RelativePath": "api/bin",
    "HttpMethod": "GET",
    "IsController": true,
    "Order": 0,
    "Parameters": [
      {
        "Name": "UserId",
        "Type": "System.Int32",
        "IsRequired": false
      }
    ],
    "ReturnTypes": []
  },
  {
    "ContainingType": "SmartBin.Api.Controllers.BinController",
    "Method": "CreateBin",
    "RelativePath": "api/bin",
    "HttpMethod": "POST",
    "IsController": true,
    "Order": 0,
    "Parameters": [
      {
        "Name": "UserId",
        "Type": "System.Int32",
        "IsRequired": false
      }
    ],
    "ReturnTypes": []
  },
  {
    "ContainingType": "SmartBin.Api.Controllers.BinController",
    "Method": "UpdateBinLocation",
    "RelativePath": "api/bin",
    "HttpMethod": "PUT",
    "IsController": true,
    "Order": 0,
    "Parameters": [
      {
        "Name": "BinId",
        "Type": "System.Int32",
        "IsRequired": false
      },
      {
        "Name": "Latitude",
        "Type": "System.Single",
        "IsRequired": false
      },
      {
        "Name": "Longitude",
        "Type": "System.Single",
        "IsRequired": false
      },
      {
        "Name": "token",
        "Type": "System.String",
        "IsRequired": false
      }
    ],
    "ReturnTypes": []
  },
  {
    "ContainingType": "SmartBin.Api.Controllers.BinController",
    "Method": "GetBinData",
    "RelativePath": "api/bin/data",
    "HttpMethod": "GET",
    "IsController": true,
    "Order": 0,
    "Parameters": [
      {
        "Name": "BinId",
        "Type": "System.Int32",
        "IsRequired": false
      },
      {
        "Name": "UserId",
        "Type": "System.Int32",
        "IsRequired": false
      }
    ],
    "ReturnTypes": []
  },
  {
    "ContainingType": "SmartBin.Api.Controllers.BinController",
    "Method": "GetBinSections",
    "RelativePath": "api/bin/section",
    "HttpMethod": "GET",
    "IsController": true,
    "Order": 0,
    "Parameters": [
      {
        "Name": "BinId",
        "Type": "System.Int32",
        "IsRequired": false
      },
      {
        "Name": "UserId",
        "Type": "System.Int32",
        "IsRequired": false
      }
    ],
    "ReturnTypes": []
  },
  {
    "ContainingType": "SmartBin.Api.Controllers.TransectionController",
    "Method": "GetTransections",
    "RelativePath": "api/transection",
    "HttpMethod": "GET",
    "IsController": true,
    "Order": 0,
    "Parameters": [
      {
        "Name": "BinId",
        "Type": "System.Int32",
        "IsRequired": false
      },
      {
        "Name": "UserId",
        "Type": "System.Int32",
        "IsRequired": false
      },
      {
        "Name": "pageNumber",
        "Type": "System.Int32",
        "IsRequired": false
      },
      {
        "Name": "pageSize",
        "Type": "System.Int32",
        "IsRequired": false
      }
    ],
    "ReturnTypes": []
  },
  {
    "ContainingType": "SmartBin.Api.Controllers.TransectionController",
    "Method": "AddTransection",
    "RelativePath": "api/transection",
    "HttpMethod": "POST",
    "IsController": true,
    "Order": 0,
    "Parameters": [
      {
        "Name": "BinId",
        "Type": "System.Int32",
        "IsRequired": false
      },
      {
        "Name": "Token",
        "Type": "System.String",
        "IsRequired": false
      },
      {
        "Name": "image",
        "Type": "Microsoft.AspNetCore.Http.IFormFile",
        "IsRequired": false
      },
      {
        "Name": "MaterialId",
        "Type": "System.Nullable\u00601[[System.Int32, System.Private.CoreLib, Version=10.0.0.0, Culture=neutral, PublicKeyToken=7cec85d7bea7798e]]",
        "IsRequired": false
      }
    ],
    "ReturnTypes": []
  }
]